ORE.py
_ORE.cpython-313-x86_64-linux-gnu.so
__init__.py
open_source_risk_engine.libs/libOREAnalytics-e5e73711.so
open_source_risk_engine.libs/libOREData-40e31c66.so
open_source_risk_engine.libs/libQuantExt-a1c8dd4f.so
open_source_risk_engine.libs/libQuantLib-50c31a72.so.1.40.0
open_source_risk_engine.libs/libboost_atomic-4a520d5e.so.1.80.0
open_source_risk_engine.libs/libboost_chrono-715b6477.so.1.80.0
open_source_risk_engine.libs/libboost_date_time-b1f3c43c.so.1.80.0
open_source_risk_engine.libs/libboost_filesystem-4fecab28.so.1.80.0
open_source_risk_engine.libs/libboost_iostreams-c22d4eb3.so.1.80.0
open_source_risk_engine.libs/libboost_log-cd41ff21.so.1.80.0
open_source_risk_engine.libs/libboost_log_setup-9a17ff59.so.1.80.0
open_source_risk_engine.libs/libboost_regex-bd5b9934.so.1.80.0
open_source_risk_engine.libs/libboost_serialization-02186684.so.1.80.0
open_source_risk_engine.libs/libboost_system-12144f47.so.1.80.0
open_source_risk_engine.libs/libboost_thread-396fa9b0.so.1.80.0
open_source_risk_engine.libs/libboost_timer-e20cfb7e.so.1.80.0
open_source_risk_engine.libs/libboost_zlib-aef6f35e.so.1.80.0
open_source_risk_engine-1.8.14.0.dist-info/METADATA
open_source_risk_engine-1.8.14.0.dist-info/WHEEL
open_source_risk_engine-1.8.14.0.dist-info/top_level.txt
open_source_risk_engine-1.8.14.0.dist-info/RECORD
open_source_risk_engine-1.8.14.0.dist-info/licenses/LICENSE.txt
