Metadata-Version: 2.1
Name: open-source-risk-engine
Version: 1.8.14.0
Summary: Python bindings for the OREAnalytics library
Home-page: http://quaternion.com
Author: Quaternion Risk Management
Author-email: info@quaternion.com
License: ORE-SWIG is
Classifier: Development Status :: 5 - Production/Stable
Classifier: Environment :: Console
Classifier: Intended Audience :: Developers
Classifier: Intended Audience :: End Users/Desktop
Classifier: License :: OSI Approved :: BSD License
Classifier: Natural Language :: English
Classifier: Operating System :: Microsoft :: Windows
Classifier: Operating System :: POSIX
Classifier: Operating System :: Unix
Classifier: Operating System :: MacOS
Classifier: Programming Language :: C++
Classifier: Programming Language :: Python
Classifier: Topic :: Scientific/Engineering
License-File: LICENSE.txt
